[{"reactionTime":0,"isBaited":true,"weight":24.3495,"catcher":"SUSAltd","baitName":"a lure worthy of weekly worship","name":"hefty viperfish","baitValue":2.3,"dateCaught":"2015-02-26 19:57:31"},{"reactionTime":0,"isBaited":false,"weight":18.6835,"catcher":"Zorael","baitName":"no bait","name":"crunchy armorfish","baitValue":1,"dateCaught":"2015-02-27 18:24:02"},{"reactionTime":0,"isBaited":false,"weight":13.6791,"catcher":"Zorael","baitName":"no bait","name":"glowing jellyfish","baitValue":1,"dateCaught":"2015-02-28 17:51:16"},{"reactionTime":0,"isBaited":false,"weight":12.6532,"catcher":"Zorael","baitName":"no bait","name":"bigeye tripodfish","baitValue":1,"dateCaught":"2015-02-27 17:46:19"},{"reactionTime":0,"isBaited":false,"weight":12.4815,"catcher":"Zorael","baitName":"no bait","name":"literary perch","baitValue":1,"dateCaught":"2015-02-27 20:34:44"},{"reactionTime":0,"isBaited":false,"weight":12.2059,"catcher":"SUSAltd","baitName":"no bait","name":"greedy trumpetfish","baitValue":1,"dateCaught":"2015-02-28 14:25:32"},{"reactionTime":0,"isBaited":false,"weight":11.9599,"catcher":"SUSAltd","baitName":"no bait","name":"fishy pilotfish","baitValue":1,"dateCaught":"2015-02-27 01:03:40"},{"reactionTime":0,"isBaited":false,"weight":10.9641,"catcher":"jeffmeng","baitName":"no bait","name":"squishy bass","baitValue":1,"dateCaught":"2015-02-27 16:19:58"},{"reactionTime":0,"isBaited":false,"weight":9.6293,"catcher":"SUSAltd","baitName":"no bait","name":"fallacious silverside","baitValue":1,"dateCaught":"2015-02-26 19:58:23"},{"reactionTime":0,"isBaited":false,"weight":9.531,"catcher":"SUSAltd","baitName":"no bait","name":"dirty springfish","baitValue":1,"dateCaught":"2015-02-26 19:59:41"},{"reactionTime":0,"isBaited":false,"weight":9.3105,"catcher":"Zorael","baitName":"no bait","name":"slimy labyrinth fish","baitValue":1,"dateCaught":"2015-02-26 23:48:10"},{"reactionTime":0,"isBaited":false,"weight":9.2316,"catcher":"SUSAltd","baitName":"no bait","name":"secret gibberfish","baitValue":1,"dateCaught":"2015-02-28 21:54:47"},{"reactionTime":0,"isBaited":false,"weight":8.9625,"catcher":"SUSAltd","baitName":"no bait","name":"gregarious lightfish","baitValue":1,"dateCaught":"2015-02-28 19:28:55"},{"reactionTime":0,"isBaited":false,"weight":8.7592,"catcher":"Zorael","baitName":"no bait","name":"fallacious flyingfish","baitValue":1,"dateCaught":"2015-02-27 20:32:28"},{"reactionTime":0,"isBaited":false,"weight":8.6913,"catcher":"SUSAltd","baitName":"no bait","name":"one-legged angelfish","baitValue":1,"dateCaught":"2015-02-26 21:47:08"},{"reactionTime":0,"isBaited":false,"weight":8.5666,"catcher":"Zorael","baitName":"no bait","name":"chocolate-covered goby","baitValue":1,"dateCaught":"2015-02-26 20:12:30"},{"reactionTime":0,"isBaited":false,"weight":8.0233,"catcher":"Zorael","baitName":"no bait","name":"electronic trunkfish","baitValue":1,"dateCaught":"2015-02-27 20:23:21"},{"reactionTime":0,"isBaited":false,"weight":8.005,"catcher":"Zorael","baitName":"no bait","name":"spike-tailed whalefish","baitValue":1,"dateCaught":"2015-02-26 23:43:21"},{"reactionTime":0,"isBaited":false,"weight":7.726,"catcher":"SUSAltd","baitName":"no bait","name":"robotic gourami","baitValue":1,"dateCaught":"2015-02-26 20:26:08"},{"reactionTime":0,"isBaited":false,"weight":7.4563,"catcher":"Zorael","baitName":"no bait","name":"dead pigfish","baitValue":1,"dateCaught":"2015-02-27 16:24:05"},{"reactionTime":0,"isBaited":false,"weight":7.3345,"catcher":"jeffmeng","baitName":"no bait","name":"sharp squaretail","baitValue":1,"dateCaught":"2015-02-27 16:45:28"},{"reactionTime":0,"isBaited":false,"weight":7.2314,"catcher":"Zorael","baitName":"no bait","name":"slithering hogsucker","baitValue":1,"dateCaught":"2015-02-27 20:28:48"},{"reactionTime":0,"isBaited":false,"weight":7.2044,"catcher":"SUSAltd","baitName":"no bait","name":"scaly longfin","baitValue":1,"dateCaught":"2015-02-27 02:21:46"},{"reactionTime":0,"isBaited":false,"weight":6.9677,"catcher":"SUSAltd","baitName":"no bait","name":"glowing squaretail","baitValue":1,"dateCaught":"2015-02-27 01:33:31"},{"reactionTime":0,"isBaited":true,"weight":6.7042,"catcher":"Zorael","baitName":"a detriment to all purposes fishing-related","name":"blanched salmon","baitValue":0.5,"dateCaught":"2015-02-27 13:08:09"},{"reactionTime":0,"isBaited":false,"weight":6.699,"catcher":"SUSAltd","baitName":"no bait","name":"robotic satrixfish","baitValue":1,"dateCaught":"2015-02-27 12:23:15"},{"reactionTime":0,"isBaited":false,"weight":6.5664,"catcher":"Zorael","baitName":"no bait","name":"glow-in-the-dark cod","baitValue":1,"dateCaught":"2015-02-28 17:34:55"},{"reactionTime":0,"isBaited":false,"weight":6.551,"catcher":"SUSAltd","baitName":"no bait","name":"expressive squaretail","baitValue":1,"dateCaught":"2015-02-28 22:01:38"},{"reactionTime":0,"isBaited":false,"weight":6.4409,"catcher":"SUSAltd","baitName":"no bait","name":"chocolate-covered treefish","baitValue":1,"dateCaught":"2015-02-26 21:14:28"},{"reactionTime":0,"isBaited":false,"weight":6.2599,"catcher":"SUSAltd","baitName":"no bait","name":"crunchy gunard","baitValue":1,"dateCaught":"2015-02-26 20:01:10"},{"reactionTime":0,"isBaited":false,"weight":5.833,"catcher":"Zorael","baitName":"no bait","name":"squishy goby","baitValue":1,"dateCaught":"2015-02-27 19:22:09"},{"reactionTime":0,"isBaited":false,"weight":5.6146,"catcher":"Zorael","baitName":"no bait","name":"sophisticated spikefish","baitValue":1,"dateCaught":"2015-02-27 20:16:16"},{"reactionTime":0,"isBaited":false,"weight":4.8509,"catcher":"SUSAltd","baitName":"no bait","name":"winged catfish","baitValue":1,"dateCaught":"2015-02-26 20:02:50"},{"reactionTime":0,"isBaited":false,"weight":4.6235,"catcher":"SUSAltd","baitName":"no bait","name":"three-legged oilfish","baitValue":1,"dateCaught":"2015-02-27 00:09:08"},{"reactionTime":0,"isBaited":false,"weight":4.4295,"catcher":"SUSAltd","baitName":"no bait","name":"oppressed pearlfish","baitValue":1,"dateCaught":"2015-02-26 23:30:16"},{"reactionTime":0,"isBaited":false,"weight":4.4233,"catcher":"SigmaWP","baitName":"no bait","name":"stinky cavefish","baitValue":1,"dateCaught":"2015-02-26 23:41:28"},{"reactionTime":0,"isBaited":false,"weight":3.8972,"catcher":"jeffmeng","baitName":"no bait","name":"amazing lampfish","baitValue":1,"dateCaught":"2015-02-27 12:35:13"}]
